{
  "_format": "hh-sol-cache-2",
  "files": {
    "D:\\Android Projects\\secure-vote-interaction\\blockchain\\contracts\\Voting.sol": {
      "lastModificationDate": 1744104510300,
      "contentHash": "26fa2dcf1bbacfb8eb425b16908f1770",
      "sourceName": "contracts/Voting.sol",
      "solcConfig": {
        "version": "0.8.19",
        "settings": {
          "optimizer": {
            "enabled": false,
            "runs": 200
          },
          "outputSelection": {
            "*": {
              "*": [
                "abi",
                "evm.bytecode",
                "evm.deployedBytecode",
                "evm.methodIdentifiers",
                "metadata"
              ],
              "": [
                "ast"
              ]
            }
          }
        }
      },
      "imports": [],
      "versionPragmas": [
        "^0.8.19"
      ],
      "artifacts": [
        "Voting"
      ]
    }
  }
}
